README.md
setup.py
radyn_xtools/README.md
radyn_xtools/__init__.py
radyn_xtools/globals.py
radyn_xtools/radyn_xtools.py
radyn_xtools/radyn_xtools_Demo.html
radyn_xtools/radyn_xtools_Demo.ipynb
radyn_xtools.egg-info/PKG-INFO
radyn_xtools.egg-info/SOURCES.txt
radyn_xtools.egg-info/dependency_links.txt
radyn_xtools.egg-info/requires.txt
radyn_xtools.egg-info/top_level.txt