Metadata-Version: 2.1
Name: radyn-xtools
Version: 1.9.4
Summary: Python analysis tools for RADYN grid output
Author: A. F. Kowalski
Author-email: adam.f.kowalski@colorado.edu
